{
  "nodes": [
    {
      "id": "node-1",
      "position": {
        "x": 257,
        "y": 249.66668701171875
      },
      "size": {
        "width": 150,
        "height": 80
      },
      "text": "新节点",
      "backgroundColor": "#e3f2fd",
      "connectionPoints": [
        {
          "id": "node-1-input",
          "type": "input",
          "position": {
            "x": 0,
            "y": -40
          }
        },
        {
          "id": "node-1-output",
          "type": "output",
          "position": {
            "x": 0,
            "y": 40
          }
        }
      ]
    },
    {
      "id": "node-2",
      "position": {
        "x": 329,
        "y": 398.66668701171875
      },
      "size": {
        "width": 150,
        "height": 80
      },
      "text": "2新节点",
      "backgroundColor": "#e3f2fd",
      "connectionPoints": [
        {
          "id": "node-2-input",
          "type": "input",
          "position": {
            "x": 0,
            "y": -40
          }
        },
        {
          "id": "node-2-output",
          "type": "output",
          "position": {
            "x": 0,
            "y": 40
          }
        }
      ]
    },
    {
      "id": "node-3",
      "position": {
        "x": 529.1321013845354,
        "y": 641.3764778990475
      },
      "size": {
        "width": 331.205439550204,
        "height": 291.6885976053785
      },
      "text": "12312313123123、12312阿斯顿jays大部分东方科技GDFKJ给付款就HGASDJ工卡觉得骄傲HSGDJK啊时感到恐惧和ASKJDH GKASJD G\nDFWEf\nwfqfqefwf",
      "backgroundColor": "#e3f2fd",
      "connectionPoints": [
        {
          "id": "node-3-input",
          "type": "input",
          "position": {
            "x": 0,
            "y": -145.84429880268925
          }
        },
        {
          "id": "node-3-output",
          "type": "output",
          "position": {
            "x": 0,
            "y": 145.84429880268925
          }
        }
      ]
    },
    {
      "id": "node-4",
      "position": {
        "x": 454.4249767837145,
        "y": 1013.8472912525506
      },
      "size": {
        "width": 150,
        "height": 80
      },
      "text": "新节点",
      "backgroundColor": "#e3f2fd",
      "connectionPoints": [
        {
          "id": "node-4-input",
          "type": "input",
          "position": {
            "x": 0,
            "y": -40
          }
        },
        {
          "id": "node-4-output",
          "type": "output",
          "position": {
            "x": 0,
            "y": 40
          }
        }
      ]
    },
    {
      "id": "node-5",
      "position": {
        "x": 716.2761701199391,
        "y": 1139.8468352832695
      },
      "size": {
        "width": 150,
        "height": 80
      },
      "text": "新节点",
      "backgroundColor": "#e3f2fd",
      "connectionPoints": [
        {
          "id": "node-5-input",
          "type": "input",
          "position": {
            "x": 0,
            "y": -40
          }
        },
        {
          "id": "node-5-output",
          "type": "output",
          "position": {
            "x": 0,
            "y": 40
          }
        }
      ]
    },
    {
      "id": "node-6",
      "position": {
        "x": 418.92483411457886,
        "y": 1211.8616119720677
      },
      "size": {
        "width": 150,
        "height": 80
      },
      "text": "新节点",
      "backgroundColor": "#e3f2fd",
      "connectionPoints": [
        {
          "id": "node-6-input",
          "type": "input",
          "position": {
            "x": 0,
            "y": -40
          }
        },
        {
          "id": "node-6-output",
          "type": "output",
          "position": {
            "x": 0,
            "y": 40
          }
        }
      ]
    }
  ],
  "edges": [
    {
      "id": "edge-1766661699948-0rdlwqvc0",
      "sourceNodeId": "node-1",
      "sourcePointId": "node-1-output",
      "targetNodeId": "node-2",
      "targetPointId": "node-2-input"
    },
    {
      "id": "edge-1766661706532-gwes832nr",
      "sourceNodeId": "node-2",
      "sourcePointId": "node-2-output",
      "targetNodeId": "node-3",
      "targetPointId": "node-3-input"
    },
    {
      "id": "edge-1766661718644-e2aywe0pe",
      "sourceNodeId": "node-3",
      "sourcePointId": "node-3-output",
      "targetNodeId": "node-4",
      "targetPointId": "node-4-input"
    },
    {
      "id": "edge-1766661724276-a7sdo7t0j",
      "sourceNodeId": "node-4",
      "sourcePointId": "node-4-output",
      "targetNodeId": "node-5",
      "targetPointId": "node-5-input"
    },
    {
      "id": "edge-1766661729898-siqj6v4nm",
      "sourceNodeId": "node-4",
      "sourcePointId": "node-4-output",
      "targetNodeId": "node-6",
      "targetPointId": "node-6-input"
    }
  ],
  "metadata": {},
  "viewState": {
    "x": 84,
    "y": -294.6666259765625,
    "scale": 0.6461745714810593
  }
}